es_fluent/__init__.py
es_fluent/builder.py
es_fluent/fields/__init__.py
es_fluent/filters/__init__.py
es_fluent/filters/core.py
es_fluent/filters/geometry.py
es_fluent/script_fields/__init__.py
es_fluent-0.0.5.dist-info/DESCRIPTION.rst
es_fluent-0.0.5.dist-info/METADATA
es_fluent-0.0.5.dist-info/metadata.json
es_fluent-0.0.5.dist-info/RECORD
es_fluent-0.0.5.dist-info/top_level.txt
es_fluent-0.0.5.dist-info/WHEEL
