Metadata-Version: 2.0
Name: es-fluent
Version: 0.0.5
Summary: Fluent API for generating elastic queries.
Home-page: https://github.com/planetlabs/es_fluent
Author: Jacob Straszynski
Author-email: jacob.straszynski@planet.com
License: Apache 2
Keywords: es_fluent
Platform: UNKNOWN
Classifier: Development Status :: 4 - Beta
Classifier: Intended Audience :: Developers
Classifier: Natural Language :: English
Classifier: Programming Language :: Python :: 2
Classifier: Programming Language :: Python :: 2.7
